calculator/__init__.py
simpleone-0.1.dist-info/LICENSE.txt
simpleone-0.1.dist-info/METADATA
simpleone-0.1.dist-info/WHEEL
simpleone-0.1.dist-info/top_level.txt
simpleone-0.1.dist-info/RECORD
