Metadata-Version: 2.1
Name: simpleone
Version: 0.1
Summary: Basic calculator
Home-page: UNKNOWN
Author: Bibekananda Nayak
Author-email: Bibekanandan892@gmail.com
License: UNKNOWN
Platform: UNKNOWN
Classifier: Programming Language :: Python :: 3
Classifier: License :: OSI Approved :: MIT License
Classifier: Operating System :: OS Independent
